composio_agno/__init__.py
composio_agno/toolset.py
composio_agno-0.7.20.dist-info/METADATA
composio_agno-0.7.20.dist-info/WHEEL
composio_agno-0.7.20.dist-info/top_level.txt
composio_agno-0.7.20.dist-info/RECORD
