Metadata-Version: 2.4
Name: composio_agno
Version: 0.7.20
Summary: Use Composio to get an array of tools with your Agno Plugin.
Home-page: https://github.com/ComposioHQ/composio
Author: Devanshu
Author-email: tech@composio.dev
Classifier: Programming Language :: Python :: 3
Classifier: License :: OSI Approved :: Apache Software License
Classifier: Operating System :: OS Independent
Requires-Dist: composio_core<0.8.0,>=0.7.0
Requires-Dist: agno
Dynamic: author
Dynamic: author-email
Dynamic: classifier
Dynamic: description
Dynamic: description-content-type
Dynamic: home-page
Dynamic: requires-dist
Dynamic: summary
